AUTHORS.rst
CONTRIBUTING.rst
HISTORY.rst
LICENSE
MANIFEST.in
README.rst
example.txt
pybozocrack.py
setup.py
docs/Makefile
docs/authors.rst
docs/conf.py
docs/contributing.rst
docs/history.rst
docs/index.rst
docs/installation.rst
docs/make.bat
docs/readme.rst
docs/usage.rst
pybozocrack.egg-info/PKG-INFO
pybozocrack.egg-info/SOURCES.txt
pybozocrack.egg-info/dependency_links.txt
pybozocrack.egg-info/entry_points.txt
pybozocrack.egg-info/not-zip-safe
pybozocrack.egg-info/top_level.txt
tests/__init__.py
tests/test_pybozocrack.py