Metadata-Version: 1.1
Name: pybozocrack
Version: 3.0.1
Summary: PyBozoCrack is a depressingly effective MD5 password hash cracker with almost zero CPU/GPU load.
Home-page: https://github.com/ikkebr/pybozocrack
Author: Henrique Pereira
Author-email: ikkibr@gmail.com
License: BSD
Keywords: pybozocrack
Platform: UNKNOWN
Classifier: Development Status :: 5 - Production/Stable
Classifier: Intended Audience :: Developers
Classifier: License :: OSI Approved :: BSD License
Classifier: Natural Language :: English
Classifier: Programming Language :: Python :: 3 :: Only
Classifier: Programming Language :: Python :: 3.6
Classifier: Programming Language :: Python :: 3.7
Classifier: Programming Language :: Python :: 3.8
Classifier: Programming Language :: Python :: 3.9
